README.md
setup.py
PrintDateTime/PrintDateTime.py
PrintDateTime.egg-info/PKG-INFO
PrintDateTime.egg-info/SOURCES.txt
PrintDateTime.egg-info/dependency_links.txt
PrintDateTime.egg-info/top_level.txt